lottelem_save_log.py
example_pkg/__init__.py
lottelem_save_log-0.0.1.dist-info/LICENSE
lottelem_save_log-0.0.1.dist-info/METADATA
lottelem_save_log-0.0.1.dist-info/WHEEL
lottelem_save_log-0.0.1.dist-info/top_level.txt
lottelem_save_log-0.0.1.dist-info/RECORD
