Metadata-Version: 2.1
Name: lottelem-save-log
Version: 0.0.1
Summary: package
Home-page: https://lcms.lottelem.co.kr
Author: shpark85
Author-email: shpark85@lotte.net
License: UNKNOWN
Platform: UNKNOWN
Classifier: Programming Language :: Python :: 3
Classifier: License :: OSI Approved :: MIT License
Classifier: Operating System :: OS Independent
